xtiff/__init__.py
xtiff/_version.py
xtiff/ome.py
xtiff/tiff.py
xtiff-0.7.9.dist-info/AUTHORS.md
xtiff-0.7.9.dist-info/LICENSE
xtiff-0.7.9.dist-info/METADATA
xtiff-0.7.9.dist-info/WHEEL
xtiff-0.7.9.dist-info/top_level.txt
xtiff-0.7.9.dist-info/zip-safe
xtiff-0.7.9.dist-info/RECORD
