Metadata-Version: 2.1
Name: xtiff
Version: 0.7.9
Summary: A tiny Python library for writing multi-channel TIFF stacks
Home-page: https://github.com/BodenmillerGroup/xtiff
Author: Jonas Windhager
Author-email: jonas.windhager@uzh.ch
License: MIT
Classifier: Operating System :: OS Independent
Classifier: Programming Language :: Python
Classifier: Programming Language :: Python :: 3
Classifier: Programming Language :: Python :: 3.8
Classifier: Programming Language :: Python :: 3.9
Classifier: Programming Language :: Python :: 3.10
Classifier: Programming Language :: Python :: 3.11
Classifier: License :: OSI Approved :: MIT License
Requires-Python: >=3.8
License-File: LICENSE
License-File: AUTHORS.md
Requires-Dist: numpy
Requires-Dist: tifffile (>=2022.4.22)
